{"Data":{"LSJZList":[{"FSRQ":"2017-02-27","DWJZ":"2.6970","LJJZ":"2.7190","SDATE":null,"ACTUALSYI":"","NAVTYPE":"1","JZZZL":"-0.11","SGZT":"开放申购","SHZT":"开放赎回","FHFCZ":"","FHFCBZ":"","DTYPE":null,"FHSP":""},{"FSRQ":"2017-02-24","DWJZ":"2.7000","LJJZ":"2.7220","SDATE":null,"ACTUALSYI":"","NAVTYPE":"1","JZZZL":"-0.44","SGZT":"开放申购","SHZT":"开放赎回","FHFCZ":"","FHFCBZ":"","DTYPE":null,"FHSP":""},{"FSRQ":"2017-02-23","DWJZ":"2.7120","LJJZ":"2.7340","SDATE":null,"ACTUALSYI":"","NAVTYPE":"1","JZZZL":"0.63","SGZT":"开放申购","SHZT":"开放赎回","FHFCZ":"","FHFCBZ":"","DTYPE":null,"FHSP":""},{"FSRQ":"2017-02-22","DWJZ":"2.6950","LJJZ":"2.7170","SDATE":null,"ACTUALSYI":"","NAVTYPE":"1","JZZZL":"0.60","SGZT":"开放申购","SHZT":"开放赎回","FHFCZ":"","FHFCBZ":"","DTYPE":null,"FHSP":""},{"FSRQ":"2017-02-21","DWJZ":"2.6790","LJJZ":"2.7010","SDATE":null,"ACTUALSYI":"","NAVTYPE":"1","JZZZL":"0.60","SGZT":"开放申购","SHZT":"开放赎回","FHFCZ":"","FHFCBZ":"","DTYPE":null,"FHSP":""},{"FSRQ":"2017-02-20","DWJZ":"2.6630","LJJZ":"2.6850","SDATE":null,"ACTUALSYI":"","NAVTYPE":"1","JZZZL":"1.06","SGZT":"开放申购","SHZT":"开放赎回","FHFCZ":"","FHFCBZ":"","DTYPE":null,"FHSP":""},{"FSRQ":"2017-02-17","DWJZ":"2.6350","LJJZ":"2.6570","SDATE":null,"ACTUALSYI":"","NAVTYPE":"1","JZZZL":"-0.98","SGZT":"开放申购","SHZT":"开放赎回","FHFCZ":"","FHFCBZ":"","DTYPE":null,"FHSP":""},{"FSRQ":"2017-02-16","DWJZ":"2.6610","LJJZ":"2.6830","SDATE":null,"ACTUALSYI":"","NAVTYPE":"1","JZZZL":"0.76","SGZT":"开放申购","SHZT":"开放赎回","FHFCZ":"","FHFCBZ":"","DTYPE":null,"FHSP":""},{"FSRQ":"2017-02-15","DWJZ":"2.6410","LJJZ":"2.6630","SDATE":null,"ACTUALSYI":"","NAVTYPE":"1","JZZZL":"0.08","SGZT":"开放申购","SHZT":"开放赎回","FHFCZ":"","FHFCBZ":"","DTYPE":null,"FHSP":""},{"FSRQ":"2017-02-14","DWJZ":"2.6390","LJJZ":"2.6610","SDATE":null,"ACTUALSYI":"","NAVTYPE":"1","JZZZL":"0.42","SGZT":"开放申购","SHZT":"开放赎回","FHFCZ":"","FHFCBZ":"","DTYPE":null,"FHSP":""},{"FSRQ":"2017-02-13","DWJZ":"2.6280","LJJZ":"2.6500","SDATE":null,"ACTUALSYI":"","NAVTYPE":"1","JZZZL":"0.42","SGZT":"开放申购","SHZT":"开放赎回","FHFCZ":"","FHFCBZ":"","DTYPE":null,"FHSP":""},{"FSRQ":"2017-02-10","DWJZ":"2.6170","LJJZ":"2.6390","SDATE":null,"ACTUALSYI":"","NAVTYPE":"1","JZZZL":"-0.04","SGZT":"开放申购","SHZT":"开放赎回","FHFCZ":"","FHFCBZ":"","DTYPE":null,"FHSP":""},{"FSRQ":"2017-02-09","DWJZ":"2.6180","LJJZ":"2.6400","SDATE":null,"ACTUALSYI":"","NAVTYPE":"1","JZZZL":"0.08","SGZT":"开放申购","SHZT":"开放赎回","FHFCZ":"","FHFCBZ":"","DTYPE":null,"FHSP":""},{"FSRQ":"2017-02-08","DWJZ":"2.6160","LJJZ":"2.6380","SDATE":null,"ACTUALSYI":"","NAVTYPE":"1","JZZZL":"0.58","SGZT":"开放申购","SHZT":"开放赎回","FHFCZ":"","FHFCBZ":"","DTYPE":null,"FHSP":""},{"FSRQ":"2017-02-07","DWJZ":"2.6010","LJJZ":"2.6230","SDATE":null,"ACTUALSYI":"","NAVTYPE":"1","JZZZL":"0.31","SGZT":"开放申购","SHZT":"开放赎回","FHFCZ":"","FHFCBZ":"","DTYPE":null,"FHSP":""},{"FSRQ":"2017-02-06","DWJZ":"2.5930","LJJZ":"2.6150","SDATE":null,"ACTUALSYI":"","NAVTYPE":"1","JZZZL":"0.89","SGZT":"开放申购","SHZT":"开放赎回","FHFCZ":"","FHFCBZ":"","DTYPE":null,"FHSP":""},{"FSRQ":"2017-02-03","DWJZ":"2.5700","LJJZ":"2.5920","SDATE":null,"ACTUALSYI":"","NAVTYPE":"1","JZZZL":"-0.35","SGZT":"开放申购","SHZT":"开放赎回","FHFCZ":"","FHFCBZ":"","DTYPE":null,"FHSP":""},{"FSRQ":"2017-01-26","DWJZ":"2.5790","LJJZ":"2.6010","SDATE":null,"ACTUALSYI":"","NAVTYPE":"1","JZZZL":"0.27","SGZT":"开放申购","SHZT":"开放赎回","FHFCZ":"","FHFCBZ":"","DTYPE":null,"FHSP":""},{"FSRQ":"2017-01-25","DWJZ":"2.5720","LJJZ":"2.5940","SDATE":null,"ACTUALSYI":"","NAVTYPE":"1","JZZZL":"0.08","SGZT":"开放申购","SHZT":"开放赎回","FHFCZ":"","FHFCBZ":"","DTYPE":null,"FHSP":""},{"FSRQ":"2017-01-24","DWJZ":"2.5700","LJJZ":"2.5920","SDATE":null,"ACTUALSYI":"","NAVTYPE":"1","JZZZL":"0.16","SGZT":"开放申购","SHZT":"开放赎回","FHFCZ":"","FHFCBZ":"","DTYPE":null,"FHSP":""},{"FSRQ":"2017-01-23","DWJZ":"2.5660","LJJZ":"2.5880","SDATE":null,"ACTUALSYI":"","NAVTYPE":"1","JZZZL":"0.90","SGZT":"开放申购","SHZT":"开放赎回","FHFCZ":"","FHFCBZ":"","DTYPE":null,"FHSP":""},{"FSRQ":"2017-01-20","DWJZ":"2.5430","LJJZ":"2.5650","SDATE":null,"ACTUALSYI":"","NAVTYPE":"1","JZZZL":"0.79","SGZT":"开放申购","SHZT":"开放赎回","FHFCZ":"","FHFCBZ":"","DTYPE":null,"FHSP":""},{"FSRQ":"2017-01-19","DWJZ":"2.5230","LJJZ":"2.5450","SDATE":null,"ACTUALSYI":"","NAVTYPE":"1","JZZZL":"-0.36","SGZT":"开放申购","SHZT":"开放赎回","FHFCZ":"","FHFCBZ":"","DTYPE":null,"FHSP":""},{"FSRQ":"2017-01-18","DWJZ":"2.5320","LJJZ":"2.5540","SDATE":null,"ACTUALSYI":"","NAVTYPE":"1","JZZZL":"0.24","SGZT":"开放申购","SHZT":"开放赎回","FHFCZ":"","FHFCBZ":"","DTYPE":null,"FHSP":""},{"FSRQ":"2017-01-17","DWJZ":"2.5260","LJJZ":"2.5480","SDATE":null,"ACTUALSYI":"","NAVTYPE":"1","JZZZL":"0.88","SGZT":"开放申购","SHZT":"开放赎回","FHFCZ":"","FHFCBZ":"","DTYPE":null,"FHSP":""},{"FSRQ":"2017-01-16","DWJZ":"2.5040","LJJZ":"2.5260","SDATE":null,"ACTUALSYI":"","NAVTYPE":"1","JZZZL":"-0.79","SGZT":"开放申购","SHZT":"开放赎回","FHFCZ":"","FHFCBZ":"","DTYPE":null,"FHSP":""},{"FSRQ":"2017-01-13","DWJZ":"2.5240","LJJZ":"2.5460","SDATE":null,"ACTUALSYI":"","NAVTYPE":"1","JZZZL":"-0.36","SGZT":"开放申购","SHZT":"开放赎回","FHFCZ":"","FHFCBZ":"","DTYPE":null,"FHSP":""},{"FSRQ":"2017-01-12","DWJZ":"2.5330","LJJZ":"2.5550","SDATE":null,"ACTUALSYI":"","NAVTYPE":"1","JZZZL":"-1.32","SGZT":"开放申购","SHZT":"开放赎回","FHFCZ":"","FHFCBZ":"","DTYPE":null,"FHSP":""},{"FSRQ":"2017-01-11","DWJZ":"2.5670","LJJZ":"2.5890","SDATE":null,"ACTUALSYI":"","NAVTYPE":"1","JZZZL":"-0.93","SGZT":"开放申购","SHZT":"开放赎回","FHFCZ":"","FHFCBZ":"","DTYPE":null,"FHSP":""},{"FSRQ":"2017-01-10","DWJZ":"2.5910","LJJZ":"2.6130","SDATE":null,"ACTUALSYI":"","NAVTYPE":"1","JZZZL":"-0.31","SGZT":"开放申购","SHZT":"开放赎回","FHFCZ":"","FHFCBZ":"","DTYPE":null,"FHSP":""},{"FSRQ":"2017-01-09","DWJZ":"2.5990","LJJZ":"2.6210","SDATE":null,"ACTUALSYI":"","NAVTYPE":"1","JZZZL":"0.31","SGZT":"开放申购","SHZT":"开放赎回","FHFCZ":"","FHFCBZ":"","DTYPE":null,"FHSP":""},{"FSRQ":"2017-01-06","DWJZ":"2.5910","LJJZ":"2.6130","SDATE":null,"ACTUALSYI":"","NAVTYPE":"1","JZZZL":"-0.73","SGZT":"开放申购","SHZT":"开放赎回","FHFCZ":"","FHFCBZ":"","DTYPE":null,"FHSP":""},{"FSRQ":"2017-01-05","DWJZ":"2.6100","LJJZ":"2.6320","SDATE":null,"ACTUALSYI":"","NAVTYPE":"1","JZZZL":"-0.34","SGZT":"开放申购","SHZT":"开放赎回","FHFCZ":"","FHFCBZ":"","DTYPE":null,"FHSP":""},{"FSRQ":"2017-01-04","DWJZ":"2.6190","LJJZ":"2.6410","SDATE":null,"ACTUALSYI":"","NAVTYPE":"1","JZZZL":"1.47","SGZT":"开放申购","SHZT":"开放赎回","FHFCZ":"","FHFCBZ":"","DTYPE":null,"FHSP":""},{"FSRQ":"2017-01-03","DWJZ":"2.5810","LJJZ":"2.6030","SDATE":null,"ACTUALSYI":"","NAVTYPE":"1","JZZZL":"-0.69","SGZT":"开放申购","SHZT":"开放赎回","FHFCZ":"","FHFCBZ":"","DTYPE":null,"FHSP":""},{"FSRQ":"2016-12-31","DWJZ":"2.5980","LJJZ":"2.6200","SDATE":null,"ACTUALSYI":"","NAVTYPE":"0","JZZZL":"-0.04","SGZT":"开放申购","SHZT":"开放赎回","FHFCZ":"","FHFCBZ":"","DTYPE":null,"FHSP":""},{"FSRQ":"2016-12-30","DWJZ":"2.5990","LJJZ":"2.6210","SDATE":null,"ACTUALSYI":"","NAVTYPE":"1","JZZZL":"0.43","SGZT":"开放申购","SHZT":"开放赎回","FHFCZ":"","FHFCBZ":"","DTYPE":null,"FHSP":""},{"FSRQ":"2016-12-29","DWJZ":"2.5880","LJJZ":"2.6100","SDATE":null,"ACTUALSYI":"","NAVTYPE":"1","JZZZL":"-0.35","SGZT":"开放申购","SHZT":"开放赎回","FHFCZ":"","FHFCBZ":"","DTYPE":null,"FHSP":""},{"FSRQ":"2016-12-28","DWJZ":"2.5970","LJJZ":"2.6190","SDATE":null,"ACTUALSYI":"","NAVTYPE":"1","JZZZL":"-0.12","SGZT":"开放申购","SHZT":"开放赎回","FHFCZ":"","FHFCBZ":"","DTYPE":null,"FHSP":""},{"FSRQ":"2016-12-27","DWJZ":"2.6000","LJJZ":"2.6220","SDATE":null,"ACTUALSYI":"","NAVTYPE":"1","JZZZL":"-0.04","SGZT":"开放申购","SHZT":"开放赎回","FHFCZ":"","FHFCBZ":"","DTYPE":null,"FHSP":""},{"FSRQ":"2016-12-26","DWJZ":"2.6010","LJJZ":"2.6230","SDATE":null,"ACTUALSYI":"","NAVTYPE":"1","JZZZL":"0.81","SGZT":"开放申购","SHZT":"开放赎回","FHFCZ":"","FHFCBZ":"","DTYPE":null,"FHSP":""},{"FSRQ":"2016-12-23","DWJZ":"2.5800","LJJZ":"2.6020","SDATE":null,"ACTUALSYI":"","NAVTYPE":"1","JZZZL":"-0.81","SGZT":"开放申购","SHZT":"开放赎回","FHFCZ":"","FHFCBZ":"","DTYPE":null,"FHSP":""},{"FSRQ":"2016-12-22","DWJZ":"2.6010","LJJZ":"2.6230","SDATE":null,"ACTUALSYI":"","NAVTYPE":"1","JZZZL":"0.23","SGZT":"开放申购","SHZT":"开放赎回","FHFCZ":"","FHFCBZ":"","DTYPE":null,"FHSP":""},{"FSRQ":"2016-12-21","DWJZ":"2.5950","LJJZ":"2.6170","SDATE":null,"ACTUALSYI":"","NAVTYPE":"1","JZZZL":"0.86","SGZT":"开放申购","SHZT":"开放赎回","FHFCZ":"","FHFCBZ":"","DTYPE":null,"FHSP":""},{"FSRQ":"2016-12-20","DWJZ":"2.5730","LJJZ":"2.5950","SDATE":null,"ACTUALSYI":"","NAVTYPE":"1","JZZZL":"0.08","SGZT":"开放申购","SHZT":"开放赎回","FHFCZ":"","FHFCBZ":"","DTYPE":null,"FHSP":""},{"FSRQ":"2016-12-19","DWJZ":"2.5710","LJJZ":"2.5930","SDATE":null,"ACTUALSYI":"","NAVTYPE":"1","JZZZL":"-0.19","SGZT":"开放申购","SHZT":"开放赎回","FHFCZ":"","FHFCBZ":"","DTYPE":null,"FHSP":""},{"FSRQ":"2016-12-16","DWJZ":"2.5760","LJJZ":"2.5980","SDATE":null,"ACTUALSYI":"","NAVTYPE":"1","JZZZL":"0.86","SGZT":"开放申购","SHZT":"开放赎回","FHFCZ":"","FHFCBZ":"","DTYPE":null,"FHSP":""},{"FSRQ":"2016-12-15","DWJZ":"2.5540","LJJZ":"2.5760","SDATE":null,"ACTUALSYI":"","NAVTYPE":"1","JZZZL":"0.24","SGZT":"开放申购","SHZT":"开放赎回","FHFCZ":"","FHFCBZ":"","DTYPE":null,"FHSP":""},{"FSRQ":"2016-12-14","DWJZ":"2.5480","LJJZ":"2.5700","SDATE":null,"ACTUALSYI":"","NAVTYPE":"1","JZZZL":"-1.43","SGZT":"开放申购","SHZT":"开放赎回","FHFCZ":"","FHFCBZ":"","DTYPE":null,"FHSP":""},{"FSRQ":"2016-12-13","DWJZ":"2.5850","LJJZ":"2.6070","SDATE":null,"ACTUALSYI":"","NAVTYPE":"1","JZZZL":"1.33","SGZT":"开放申购","SHZT":"开放赎回","FHFCZ":"","FHFCBZ":"","DTYPE":null,"FHSP":""}],"FundType":"002","SYType":null},"ErrCode":0,"ErrMsg":null,"TotalCount":1493,"Expansion":null,"PageSize":50,"PageIndex":7}